{"name":"slidersTest1","id":"handlingWebELements.MouseMovements.HandlingSliders:slidersTest1","testCaseName":"handlingWebELements.MouseMovements.HandlingSliders","userStory":{"id":"handlingWebELements.MouseMovements.HandlingSliders","storyName":"Handling sliders","storyClassName":"handlingWebELements.MouseMovements.HandlingSliders","path":"handlingWebELements.MouseMovements","type":"story"},"featureTag":{"name":"Mouse movements/Handling sliders","type":"story","displayName":"Mouse movements/Handling sliders"},"title":"To illustrate how to handle the sliders using the withActions API method called dragAndDropBy(WebElement,x-axis,y-axis)","tags":[{"name":"Mouse movements/Handling sliders","type":"story","displayName":"Mouse movements/Handling sliders"}],"startTime":"2021-01-21T16:17:22.783+05:30[Asia/Calcutta]","duration":21641,"projectKey":"","sessionId":"93ae09a6518e3d17efd1d3f32332fb83","driver":"chrome","isManualTestingUpToDate":false,"manual":false,"testSource":"JUnit","result":"SUCCESS"}